dftoltx/__init__.py
dftoltx/generator.py
dftoltx-0.0.4.dist-info/LICENSE
dftoltx-0.0.4.dist-info/METADATA
dftoltx-0.0.4.dist-info/WHEEL
dftoltx-0.0.4.dist-info/top_level.txt
dftoltx-0.0.4.dist-info/RECORD
